f_work_mcp/__init__.py
f_work_mcp/cli.py
f_work_mcp/gui.py
f_work_mcp/server.py
f_work_mcp/tracker.py
f_work_mcp-1.0.0.dist-info/METADATA
f_work_mcp-1.0.0.dist-info/WHEEL
f_work_mcp-1.0.0.dist-info/entry_points.txt
f_work_mcp-1.0.0.dist-info/licenses/LICENSE
f_work_mcp-1.0.0.dist-info/RECORD
