Metadata-Version: 2.4
Name: f-work-mcp
Version: 1.0.0
Summary: A MCP server for tracking work progress and generating daily reports with Python file diff analysis
Project-URL: Homepage, https://github.com/your-username/f-work-mcp
Project-URL: Documentation, https://github.com/your-username/f-work-mcp#readme
Project-URL: Repository, https://github.com/your-username/f-work-mcp
Project-URL: Issues, https://github.com/your-username/f-work-mcp/issues
Project-URL: Changelog, https://github.com/your-username/f-work-mcp/blob/main/CHANGELOG.md
Author-email: F-Work MCP Team <contact@f-work-mcp.com>
Maintainer-email: F-Work MCP Team <contact@f-work-mcp.com>
License: MIT
License-File: LICENSE
Keywords: daily-report,git,mcp,productivity,python,work-tracking
Classifier: Development Status :: 4 - Beta
Classifier: Intended Audience :: Developers
Classifier: License :: OSI Approved :: MIT License
Classifier: Operating System :: OS Independent
Classifier: Programming Language :: Python :: 3
Classifier: Programming Language :: Python :: 3.10
Classifier: Programming Language :: Python :: 3.11
Classifier: Programming Language :: Python :: 3.12
Classifier: Programming Language :: Python :: 3.13
Classifier: Topic :: Office/Business :: Scheduling
Classifier: Topic :: Software Development :: Libraries :: Python Modules
Classifier: Topic :: Software Development :: Version Control :: Git
Classifier: Topic :: Utilities
Requires-Python: >=3.10
Requires-Dist: mcp[cli]>=1.12.2
Requires-Dist: pydantic>=2.0.0
Requires-Dist: starlette>=0.27.0
Provides-Extra: dev
Requires-Dist: black>=23.0.0; extra == 'dev'
Requires-Dist: build>=1.0.0; extra == 'dev'
Requires-Dist: flake8>=6.0.0; extra == 'dev'
Requires-Dist: isort>=5.12.0; extra == 'dev'
Requires-Dist: mypy>=1.0.0; extra == 'dev'
Requires-Dist: pre-commit>=3.0.0; extra == 'dev'
Requires-Dist: pytest-asyncio>=0.21.0; extra == 'dev'
Requires-Dist: pytest>=7.0.0; extra == 'dev'
Requires-Dist: twine>=4.0.0; extra == 'dev'
Provides-Extra: test
Requires-Dist: pytest-asyncio>=0.21.0; extra == 'test'
Requires-Dist: pytest-cov>=4.0.0; extra == 'test'
Requires-Dist: pytest>=7.0.0; extra == 'test'
